chug/__init__.py
chug/model.py
chug/writers.py
chug/parsers/__init__.py
chug/parsers/core.py
chug/parsers/rest.py
changelog_chug-0.0.3.dist-info/COPYING
changelog_chug-0.0.3.dist-info/LICENSE.AGPL-3
changelog_chug-0.0.3.dist-info/METADATA
changelog_chug-0.0.3.dist-info/WHEEL
changelog_chug-0.0.3.dist-info/top_level.txt
changelog_chug-0.0.3.dist-info/RECORD
