Metadata-Version: 2.1
Name: changelog-chug
Version: 0.0.3
Summary: Parser library for project Change Log documents.
Author-email: Ben Finney <ben+python@benfinney.id.au>
Maintainer: Ben Finney <ben+python@benfinney.id>
License: Copying this work
Project-URL: Home Page, https://git.sr.ht/~bignose/changelog-chug
Project-URL: Change Log,     https://git.sr.ht/~bignose/changelog-chug/tree/main/item/ChangeLog
Project-URL: Source, https://git.sr.ht/~bignose/changelog-chug
Project-URL: Issue Tracker, https://todo.sr.ht/~bignose/changelog-chug
Keywords: version,changelog,release,packaging
Classifier: Development Status :: 2 - Pre-Alpha
Classifier: License :: OSI Approved :: GNU Affero General Public License v3 or later (AGPLv3+)
Classifier: Programming Language :: Python :: 3
Classifier: Intended Audience :: Developers
Classifier: Topic :: Software Development :: Build Tools
Requires-Python: >=3.7
License-File: LICENSE.AGPL-3
License-File: COPYING
Requires-Dist: semver >=3.0.0
Requires-Dist: docutils >=0.21.0
Provides-Extra: build
Requires-Dist: changelog-chug[devel] ; extra == 'build'
Requires-Dist: wheel ; extra == 'build'
Requires-Dist: build ; extra == 'build'
Provides-Extra: devel
Requires-Dist: changelog-chug[test] ; extra == 'devel'
Requires-Dist: pyupgrade ~=3.17 ; extra == 'devel'
Requires-Dist: isort ~=5.13 ; extra == 'devel'
Provides-Extra: publish
Requires-Dist: changelog-chug[build] ; extra == 'publish'
Requires-Dist: twine ; extra == 'publish'
Provides-Extra: static-analysis
Requires-Dist: pip-check ; extra == 'static-analysis'
Requires-Dist: mccabe ~=0.7 ; extra == 'static-analysis'
Requires-Dist: pycodestyle ~=2.12 ; extra == 'static-analysis'
Requires-Dist: ruff ~=0.6 ; extra == 'static-analysis'
Provides-Extra: test
Requires-Dist: changelog-chug[static-analysis] ; extra == 'test'
Requires-Dist: testtools ; extra == 'test'
Requires-Dist: testscenarios >=0.4 ; extra == 'test'
Requires-Dist: coverage ; extra == 'test'
